plotgpt.py
plotgpt-0.1.0.dist-info/METADATA
plotgpt-0.1.0.dist-info/WHEEL
plotgpt-0.1.0.dist-info/RECORD
