Metadata-Version: 2.1
Name: plotgpt
Version: 0.1.0
Summary: A tiny ai to help you visualize data
Author: Stephen Ma
Author-email: stphnma@gmail.com
Requires-Python: >=3.10,<4.0
Classifier: Programming Language :: Python :: 3
Classifier: Programming Language :: Python :: 3.10
Classifier: Programming Language :: Python :: 3.11
Requires-Dist: langchain (>=0.0.150,<0.0.151)
Requires-Dist: matplotlib (>=3.7.1,<4.0.0)
Requires-Dist: pandas (>=2.0.1,<3.0.0)
Requires-Dist: seaborn (>=0.12.2,<0.13.0)
Requires-Dist: tiktoken (>=0.3.3,<0.4.0)
